<annotation>
	<folder>train</folder>
	<filename>23.jpg</filename>
	<path>/home/mateus/Documentos/API/API_6_Semestre_IA/dataset/imagens/train/23.jpg</path>
	<source>
		<database>Unknown</database>
	</source>
	<size>
		<width>2000</width>
		<height>1325</height>
		<depth>3</depth>
	</size>
	<segmented>0</segmented>
	<object>
		<name>person</name>
		<pose>Unspecified</pose>
		<truncated>0</truncated>
		<difficult>0</difficult>
		<bndbox>
			<xmin>661</xmin>
			<ymin>491</ymin>
			<xmax>1335</xmax>
			<ymax>1322</ymax>
		</bndbox>
	</object>
</annotation>
